{"cameraMode":{"drawMode":0,"name":"Shaded","section":"Shading Mode"},"sceneLighting":true,"audioPlay":false,"sceneViewState":{"showFog":true,"showMaterialUpdate":false,"showSkybox":true,"showFlares":true,"showImageEffects":true,"showParticleSystems":true},"in2DMode":false,"pivot":{"x":1.0523324012756348,"y":1.774864673614502,"z":-0.44728100299835207},"rotation":{"x":0.09743549674749375,"y":-0.33076542615890505,"z":0.034356918185949329,"w":0.9380415081977844},"size":0.5894497632980347,"orthographic":false}